PyxelUniversalFont/__init__.py
PyxelUniversalFont/command.py
PyxelUniversalFont/sample_app.py
PyxelUniversalFont/fonts/IPA_Gothic.ttf
PyxelUniversalFont/fonts/IPA_Mincho.ttf
PyxelUniversalFont/fonts/IPA_PGothic.ttf
PyxelUniversalFont/fonts/IPA_PMincho.ttf
PyxelUniversalFont/fonts/misaki_gothic.ttf
PyxelUniversalFont/fonts/misaki_gothic2.ttf
PyxelUniversalFont/fonts/misaki_mincho.ttf
PyxelUniversalFont/src/__init__.py
PyxelUniversalFont/src/root.py
PyxelUniversalFont/src/utils.py
pyxel_universal_font-1.1.1.dist-info/LICENSE
pyxel_universal_font-1.1.1.dist-info/METADATA
pyxel_universal_font-1.1.1.dist-info/WHEEL
pyxel_universal_font-1.1.1.dist-info/entry_points.txt
pyxel_universal_font-1.1.1.dist-info/top_level.txt
pyxel_universal_font-1.1.1.dist-info/RECORD
