Metadata-Version: 2.1
Name: pyxel-universal-font
Version: 1.1.1
Summary: An extension tool to add fonts to the public "pyxel" library.
Home-page: https://github.com/n-koba0427/PyxelUniversalFont
Author: naoyashi
Author-email: n.koba0427@gmail.com
Classifier: License :: OSI Approved :: MIT License
Classifier: Programming Language :: Python
Classifier: Programming Language :: Python :: 3
Classifier: Programming Language :: Python :: 3.11
Classifier: Development Status :: 5 - Production/Stable
Classifier: Intended Audience :: Developers
Classifier: Natural Language :: Japanese
License-File: LICENSE
